i2s_in.v
// channels ALMOST build words correctly, only the output logic is the issue
// bcz valid never goes high

// LSB always padded with a zero???

module transceiver_in #(
    parameter WIDTH = 24,
    parameter COUNTER_BITS = 5    // 5 bits covers 0–24
)(
    // general state
    input  wire             rst_n,
    input  wire             clk, // doubles as sck

    // incoming
    input  wire             ws,
    input  wire             sd,

    // outgoing
    input wire              o_tready,
    output reg              o_tvalid,
    output reg  [WIDTH-1:0] tdata
);

reg r_ws, r_sd;
reg r_ws_last;
reg new_word_temp;

reg state; // 0 is idle, 1 is processing word

reg [COUNTER_BITS-1:0] word_counter;

reg [WIDTH-1:0] channel_1;
reg [WIDTH-1:0] channel_2;

always @(posedge clk) begin

    if (!rst_n) begin // reset logic
        o_tvalid     <= 1'b0;
        tdata        <= {WIDTH{1'b0}}; 

        r_sd         <= 1'b0;
        r_ws         <= ws;
        r_ws_last    <= ws;

        word_counter <= 5'b0;
        channel_1    <= 24'b0;
        channel_2    <= 24'b0;
        state        <= 1'b0;
    end 
    
    else begin
        // latch inputs (1 cycle delayed) for stability
        r_ws <= ws;
        r_sd <= sd;

        // Handle AXI-S handshake backpressure
        // if (o_tready && o_tvalid) begin
        //     o_tvalid <= 1'b0; 
        // end

        // ── NEW WORD DETECTED (WS EDGE) ─────────
        if (r_ws_last != r_ws) begin
            r_ws_last    <= r_ws;
            word_counter <= 5'b0; // Reset counter, wait for NEXT cycle to sample MSB
            state        <= 1'b1;
            
            // Handle back-to-back I2S words safely (WS toggling exactly at word end)
            if (state != 0 && word_counter == WIDTH) begin
                // o_tvalid <= 1'b1;
                // Reading old value of r_ws_last here correctly grabs the finished channel
                tdata    <= r_ws_last ? channel_2 : channel_1;
            end
        end
        // ── SHIFTING DATA ──
        else if (state != 0) begin
            if (word_counter == WIDTH - 1) begin // HAS TO BE -1 OR ELSE NOT TRIGGERED.
                // WAS MISSING WRITE FOR LSB
                o_tvalid <= 1'b1;
                $display("WORD END");
                state    <= 1'b0; // back to idle
                tdata    <= r_ws ? {channel_2[23:1], r_sd} : {channel_1[23:1], r_sd}; 
            end else begin
                // Write to bit [WIDTH-1 - word_counter]
                if (r_ws)
                    channel_2[WIDTH - 1 - word_counter] <= r_sd;
                else
                    channel_1[WIDTH - 1 - word_counter] <= r_sd;
                
                word_counter <= word_counter + 5'd1;

                // TEMPORARY VALID DE-ASSERTION FIX
                if(word_counter == 5) begin
                    o_tvalid <= 1'b0;
                end
            end
        end
    end
end
endmodule

actual_tb.v
`timescale 1ns / 1ps
`include "i2s_in.v"

module transceiver_in_tb;

    // Clock and reset
    reg clk;
    reg rst_n;
    reg test_over;

    // DUT ports
    reg        ws;
    reg        sd;
    reg        o_tready;
    wire       o_tvalid;
    wire [23:0] tdata;

    // -------------------------------------------------------------------------
    // Test vectors
    // -------------------------------------------------------------------------
    reg [23:0] src_data [0:3];   // a few words for the demo
    integer    data_counter;    // counts bits transmitted for the current word
    integer    word_counter;    // counts words transmitted

    // ──── DUT ─────
    transceiver_in #(
        .WIDTH(24),
        .COUNTER_BITS(5)
    ) dut (
        .clk      (clk),
        .rst_n    (rst_n),
        .ws       (ws),
        .sd       (sd),
        .o_tready (o_tready),
        .o_tvalid (o_tvalid),
        .tdata    (tdata)
    );

    // ── Clock: 10 ns period ──
    initial begin
        clk = 1'b0;
        o_tready = 1'b1;
        forever #5 clk = ~clk;
    end

  // -------------------------------------------------------------------------
  // Test stimulus
  // -------------------------------------------------------------------------
  initial begin
    // -------------------------------------------------
    // Dump waveform for later inspection
    // -------------------------------------------------
    $dumpfile("actual_tb.vcd");
    $dumpvars(0, transceiver_in_tb);

    // -------------------------------------------------
    // Initialise registers
    // -------------------------------------------------
    rst_n = 0;          // keep DUT in reset initially
    ws    = 0;
    sd    = 0;
    data_counter = 0;
    word_counter = 0;
    test_over = 0;

    // --------- test words --------------
    // src_data[0] = 24'hABCDEF; // 101010111100110111101111
    // src_data[1] = 24'h123456; // 000100100011010001010110
    // src_data[2] = 24'hBADBAD; // 101110101101101110101101
    // src_data[3] = 24'hF0000D; // 111100000000000000001101

    // ----------straight high -----------
    // src_data[0] = 24'b111111111111111111111111;
    // src_data[1] = 24'b111111111111111111111111;
    // src_data[2] = 24'b111111111111111111111111;
    // src_data[3] = 24'b111111111111111111111111;

    // ---------- spot boundary issues between words ----------
    src_data[0] = {24{1'b1}};
    src_data[1] = {24{1'b0}};
    src_data[2] = {24{1'b1}};
    src_data[3] = {24{1'b0}};

    // ---------- easy to spot patterns ---------
    // src_data[0] = 24'b010101010101010101010101; // 1-1-1-1
    // src_data[1] = 24'b001100110011001100110011; // 2-2-2-2
    // src_data[2] = 24'b000111000111000111000111; // 3-3-3-3
    // src_data[3] = 24'b000011110000111100001111; // 4-4-4-4

    // -------------------------------------------------
    // Release reset after a couple of clock edges
    // -------------------------------------------------
    #40 rst_n = 1;  // de‑assert reset

    // change to 1: makes sure that it gets triggered within loop
    ws = 1'b1;
    #10

    // -------------------------------------------------
    // Transmit all words, LSB‑first, one bit per clock
    // -------------------------------------------------
    for (word_counter = 0; word_counter < 4; word_counter = word_counter + 1) begin
      // WS is high for the left channel, low for the right channel.
      // For simplicity we toggle it every 32 bits.
      ws <= word_counter[0];   // 0,1,0,1 … (alternates each word)

      // Send 24 bits of the current word, MSB first
      for (data_counter = 0; data_counter < 24; data_counter = data_counter + 1) begin
        // Subtract from 23 to grab the top bits first
        sd <= src_data[word_counter][23 - data_counter]; 
        @(posedge clk);
      end

      #20;
    end

    // -------------------------------------------------
    // 6Wait for the DUT to raise `valid` and capture the last word
    // -------------------------------------------------
    // @(posedge o_tvalid);
    // $display("----- Received word -----");
    // $display("  Expected : %h", src_data[word_counter-1]);
    // $display("  DUT out  : %h", tdata);
    // $display("--------------------------");

    // -------------------------------------------------
    // Finish simulation
    // -------------------------------------------------
    test_over = 1;
    #100 $finish;
  end
endmodule

actual_tb.vcd
$date
	Sun Jun  7 11:43:33 2026
$end
$version
	Icarus Verilog
$end
$timescale
	1ps
$end
$scope module transceiver_in_tb $end
$var wire 24 ! tdata [23:0] $end
$var wire 1 " o_tvalid $end
$var reg 1 # clk $end
$var reg 1 $ o_tready $end
$var reg 1 % rst_n $end
$var reg 1 & sd $end
$var reg 1 ' test_over $end
$var reg 1 ( ws $end
$var integer 32 ) data_counter [31:0] $end
$var integer 32 * word_counter [31:0] $end
$scope module dut $end
$var wire 1 # clk $end
$var wire 1 $ o_tready $end
$var wire 1 % rst_n $end
$var wire 1 & sd $end
$var wire 1 ( ws $end
$var parameter 32 + COUNTER_BITS $end
$var parameter 32 , WIDTH $end
$var reg 24 - channel_1 [23:0] $end
$var reg 24 . channel_2 [23:0] $end
$var reg 1 " o_tvalid $end
$var reg 1 / r_sd $end
$var reg 1 0 r_ws $end
$var reg 1 1 r_ws_last $end
$var reg 1 2 state $end
$var reg 24 3 tdata [23:0] $end
$var reg 5 4 word_counter [4:0] $end
$upscope $end
$upscope $end
$enddefinitions $end
$comment Show the parameter values. $end
$dumpall
b11000 ,
b101 +
$end
#0
$dumpvars
bx 4
bx 3
x2
x1
x0
x/
bx .
bx -
b0 *
b0 )
0(
0'
0&
0%
1$
0#
x"
bx !
$end
#5000
02
b0 .
b0 -
b0 4
01
00
0/
b0 !
b0 3
0"
1#
#10000
0#
#15000
1#
#20000
0#
#25000
1#
#30000
0#
#35000
1#
#40000
0#
1(
1%
#45000
10
1#
#50000
1&
0(
0#
#55000
12
11
1/
00
b1 )
1#
#60000
0#
#65000
01
b10 )
1#
#70000
0#
#75000
b1 4
b100000000000000000000000 -
b11 )
1#
#80000
0#
#85000
b10 4
b110000000000000000000000 -
b100 )
1#
#90000
0#
#95000
b11 4
b111000000000000000000000 -
b101 )
1#
#100000
0#
#105000
b100 4
b111100000000000000000000 -
b110 )
1#
#110000
0#
#115000
b101 4
b111110000000000000000000 -
b111 )
1#
#120000
0#
#125000
b110 4
b111111000000000000000000 -
b1000 )
1#
#130000
0#
#135000
b111 4
b111111100000000000000000 -
b1001 )
1#
#140000
0#
#145000
b1000 4
b111111110000000000000000 -
b1010 )
1#
#150000
0#
#155000
b1001 4
b111111111000000000000000 -
b1011 )
1#
#160000
0#
#165000
b1010 4
b111111111100000000000000 -
b1100 )
1#
#170000
0#
#175000
b1011 4
b111111111110000000000000 -
b1101 )
1#
#180000
0#
#185000
b1100 4
b111111111111000000000000 -
b1110 )
1#
#190000
0#
#195000
b1101 4
b111111111111100000000000 -
b1111 )
1#
#200000
0#
#205000
b1110 4
b111111111111110000000000 -
b10000 )
1#
#210000
0#
#215000
b1111 4
b111111111111111000000000 -
b10001 )
1#
#220000
0#
#225000
b10000 4
b111111111111111100000000 -
b10010 )
1#
#230000
0#
#235000
b10001 4
b111111111111111110000000 -
b10011 )
1#
#240000
0#
#245000
b10010 4
b111111111111111111000000 -
b10100 )
1#
#250000
0#
#255000
b10011 4
b111111111111111111100000 -
b10101 )
1#
#260000
0#
#265000
b10100 4
b111111111111111111110000 -
b10110 )
1#
#270000
0#
#275000
b10101 4
b111111111111111111111000 -
b10111 )
1#
#280000
0#
#285000
b10110 4
b111111111111111111111100 -
b11000 )
1#
#290000
0#
#295000
b10111 4
b111111111111111111111110 -
1#
#300000
0#
#305000
b111111111111111111111111 !
b111111111111111111111111 3
02
1"
0&
1(
1#
b1 )
b1 *
#310000
0#
#315000
0/
10
b10 )
1#
#320000
0#
#325000
12
b0 4
11
b11 )
1#
#330000
0#
#335000
b1 4
b100 )
1#
#340000
0#
#345000
b10 4
b101 )
1#
#350000
0#
#355000
b11 4
b110 )
1#
#360000
0#
#365000
b100 4
b111 )
1#
#370000
0#
#375000
b101 4
b1000 )
1#
#380000
0#
#385000
0"
b110 4
b1001 )
1#
#390000
0#
#395000
b111 4
b1010 )
1#
#400000
0#
#405000
b1000 4
b1011 )
1#
#410000
0#
#415000
b1001 4
b1100 )
1#
#420000
0#
#425000
b1010 4
b1101 )
1#
#430000
0#
#435000
b1011 4
b1110 )
1#
#440000
0#
#445000
b1100 4
b1111 )
1#
#450000
0#
#455000
b1101 4
b10000 )
1#
#460000
0#
#465000
b1110 4
b10001 )
1#
#470000
0#
#475000
b1111 4
b10010 )
1#
#480000
0#
#485000
b10000 4
b10011 )
1#
#490000
0#
#495000
b10001 4
b10100 )
1#
#500000
0#
#505000
b10010 4
b10101 )
1#
#510000
0#
#515000
b10011 4
b10110 )
1#
#520000
0#
#525000
b10100 4
b10111 )
1#
#530000
0#
#535000
b10101 4
b11000 )
1#
#540000
0#
#545000
b10110 4
1#
#550000
0#
#555000
b10111 4
1&
0(
1#
b1 )
b10 *
#560000
0#
#565000
b0 !
b0 3
02
1"
1/
00
b10 )
1#
#570000
0#
#575000
12
b0 4
01
b11 )
1#
#580000
0#
#585000
b1 4
b100 )
1#
#590000
0#
#595000
b10 4
b101 )
1#
#600000
0#
#605000
b11 4
b110 )
1#
#610000
0#
#615000
b100 4
b111 )
1#
#620000
0#
#625000
b101 4
b1000 )
1#
#630000
0#
#635000
0"
b110 4
b1001 )
1#
#640000
0#
#645000
b111 4
b1010 )
1#
#650000
0#
#655000
b1000 4
b1011 )
1#
#660000
0#
#665000
b1001 4
b1100 )
1#
#670000
0#
#675000
b1010 4
b1101 )
1#
#680000
0#
#685000
b1011 4
b1110 )
1#
#690000
0#
#695000
b1100 4
b1111 )
1#
#700000
0#
#705000
b1101 4
b10000 )
1#
#710000
0#
#715000
b1110 4
b10001 )
1#
#720000
0#
#725000
b1111 4
b10010 )
1#
#730000
0#
#735000
b10000 4
b10011 )
1#
#740000
0#
#745000
b10001 4
b10100 )
1#
#750000
0#
#755000
b10010 4
b10101 )
1#
#760000
0#
#765000
b10011 4
b10110 )
1#
#770000
0#
#775000
b10100 4
b10111 )
1#
#780000
0#
#785000
b10101 4
b11000 )
1#
#790000
0#
#795000
b10110 4
1#
#800000
0#
#805000
b10111 4
0&
1(
1#
b1 )
b11 *
#810000
0#
#815000
b111111111111111111111111 !
b111111111111111111111111 3
02
1"
0/
10
b10 )
1#
#820000
0#
#825000
12
b0 4
11
b11 )
1#
#830000
0#
#835000
b1 4
b100 )
1#
#840000
0#
#845000
b10 4
b101 )
1#
#850000
0#
#855000
b11 4
b110 )
1#
#860000
0#
#865000
b100 4
b111 )
1#
#870000
0#
#875000
b101 4
b1000 )
1#
#880000
0#
#885000
0"
b110 4
b1001 )
1#
#890000
0#
#895000
b111 4
b1010 )
1#
#900000
0#
#905000
b1000 4
b1011 )
1#
#910000
0#
#915000
b1001 4
b1100 )
1#
#920000
0#
#925000
b1010 4
b1101 )
1#
#930000
0#
#935000
b1011 4
b1110 )
1#
#940000
0#
#945000
b1100 4
b1111 )
1#
#950000
0#
#955000
b1101 4
b10000 )
1#
#960000
0#
#965000
b1110 4
b10001 )
1#
#970000
0#
#975000
b1111 4
b10010 )
1#
#980000
0#
#985000
b10000 4
b10011 )
1#
#990000
0#
#995000
b10001 4
b10100 )
1#
#1000000
0#
#1005000
b10010 4
b10101 )
1#
#1010000
0#
#1015000
b10011 4
b10110 )
1#
#1020000
0#
#1025000
b10100 4
b10111 )
1#
#1030000
0#
#1035000
b10101 4
b11000 )
1#
#1040000
0#
#1045000
b10110 4
1#
#1050000
0#
#1055000
b10111 4
1#
1'
b100 *
#1060000
0#
#1065000
b0 !
b0 3
02
1"
1#
