i2s_in.v
// still drops first word after reset, but that's fine

module transceiver_in #(
    parameter WIDTH = 24,
    parameter COUNTER_BITS = 5    // 5 bits covers 0–24
)(
    input  wire        rst_n,
    input  wire        sck,
    input  wire        ws,
    input  wire        sd,
    output reg         valid,
    output reg  [WIDTH-1:0] data
);

reg r_ws, r_sd;
reg r_ws_last;

reg [COUNTER_BITS-1:0] word_counter;  // 0 = idle, 1..WIDTH = capturing

reg [WIDTH-1:0] channel_1;
reg [WIDTH-1:0] channel_2;

always @(posedge sck) begin

    if (!rst_n) begin
        valid        <= 1'b0;
        data         <= 24'b0;

        r_sd         <= 1'b0;
        r_ws         <= ws;
        r_ws_last    <= ws;            // ← FIX 1: match, don't force fake edge

        word_counter <= 5'b0;          // ← idle
        channel_1    <= 24'b0;
        channel_2    <= 24'b0;
    end

    else begin
        // latch inputs (1 cycle delayed)
        r_ws <= ws;
        r_sd <= sd;

        // ── NEW WORD DETECTED ──────────────────────────
        if (r_ws_last != r_ws) begin
            valid        <= 1'b0;
            word_counter <= 5'd1;                     // start capturing
            r_ws_last    <= r_ws;

            // write MSB (bit WIDTH-1)
            if (r_ws)
                channel_2[WIDTH-1] <= r_sd;
            else
                channel_1[WIDTH-1] <= r_sd;
        end

        // ── NO NEW WORD ───────────────────────────────
        else begin

            if (word_counter == 5'd0) begin
                // idle — waiting for first WS edge after reset
                // do nothing
            end

            else if (word_counter == (WIDTH - 1)) begin // end of word

                valid        <= 1'b1;
                word_counter <= 5'd0;                 // back to idle

                // concatenate data bcz it gets dropped otherwise

                if (r_ws)
                    data <= {channel_2[WIDTH-1:1], r_sd}; 
                else
                    data <= {channel_1[WIDTH-1:1], r_sd}; 
            end

            else begin                                // word_counter = 1..WIDTH-1
                // write to bit [WIDTH-1 - word_counter]
                // counter=1 → bit 22, counter=23 → bit 0
                if (r_ws)
                    channel_2[WIDTH-1 - word_counter] <= r_sd;
                else
                    channel_1[WIDTH-1 - word_counter] <= r_sd;

                word_counter <= word_counter + 5'd1;
            end
        end
    end
end

endmodule

i2s_in_tb.v
`timescale 1ns / 1ns
`include "i2s_in.v"

module transceiver_in_tb;

  // -------------------------------------------------------------------------
  // UUT ports
  // -------------------------------------------------------------------------
  reg         i_rst_n;

  reg         i_sck = 0;
  reg         i_ws;
  reg         i_sd;

  wire        o_valid;
  wire [23:0] o_data;

  // -------------------------------------------------------------------------
  // Test vectors
  // -------------------------------------------------------------------------
  reg [23:0] src_data [0:3];   // a few words for the demo
  integer    data_counter;    // counts bits transmitted for the current word
  integer    word_counter;    // counts words transmitted

  // instantiate test module
  transceiver_in uut (
      .rst_n (i_rst_n),
      .sck   (i_sck),
      .ws    (i_ws),
      .sd    (i_sd),
      .valid (o_valid),
      .data  (o_data)
  );

  // toggle clock every 10ns (20ns cycle time)
  always begin
    i_sck = ~i_sck;
    #10;
  end

  



  // -------------------------------------------------------------------------
  // Test stimulus
  // -------------------------------------------------------------------------
  initial begin
    // -------------------------------------------------
    // Dump waveform for later inspection
    // -------------------------------------------------
    $dumpfile("i2s_in_tb.vcd");
    $dumpvars(0, transceiver_in_tb);

    // -------------------------------------------------
    // Initialise registers
    // -------------------------------------------------
    i_rst_n = 0;          // keep DUT in reset initially
    i_ws    = 0;
    i_sd    = 0;
    data_counter = 0;
    word_counter = 0;

    // -------------------------------------------------
    // Test words (6 HEX CHARACTERS * 4bit per = 24 bit per word)
    // -------------------------------------------------

    src_data[0] = 24'hABCDEF;
    src_data[1] = 24'h123456;
    src_data[2] = 24'hBADBAD;
    src_data[3] = 24'hF0000D;

    // -------------------------------------------------
    // Release reset after a couple of clock edges
    // -------------------------------------------------
    #40 i_rst_n = 1;  // de‑assert reset

    // -------------------------------------------------
    // Transmit all words, LSB‑first, one bit per clock
    // -------------------------------------------------
    for (word_counter = 0; word_counter < 4; word_counter = word_counter + 1) begin
      // WS is high for the left channel, low for the right channel.
      // For simplicity we toggle it every 32 bits.
      i_ws <= word_counter[0];   // 0,1,0,1 … (alternates each word)

      // Send 24 bits of the current word, MSB first
      for (data_counter = 0; data_counter < 24; data_counter = data_counter + 1) begin
        // Subtract from 23 to grab the top bits first
        i_sd <= src_data[word_counter][23 - data_counter]; 
        @(posedge i_sck);
      end
    end

    // -------------------------------------------------
    // Finish simulation
    // -------------------------------------------------
    #100 $finish;
  end

endmodule

i2s_in_tb.vcd
$date
	Fri Jun  5 21:35:36 2026
$end
$version
	Icarus Verilog
$end
$timescale
	1ns
$end
$scope module transceiver_in_tb $end
$var wire 1 ! o_valid $end
$var wire 24 " o_data [23:0] $end
$var reg 1 # i_rst_n $end
$var reg 1 $ i_sck $end
$var reg 1 % i_sd $end
$var reg 1 & i_ws $end
$var integer 32 ' data_counter [31:0] $end
$var integer 32 ( word_counter [31:0] $end
$scope module uut $end
$var wire 1 # rst_n $end
$var wire 1 $ sck $end
$var wire 1 % sd $end
$var wire 1 & ws $end
$var parameter 32 ) COUNTER_BITS $end
$var parameter 32 * WIDTH $end
$var reg 24 + channel_1 [23:0] $end
$var reg 24 , channel_2 [23:0] $end
$var reg 24 - data [23:0] $end
$var reg 1 . r_sd $end
$var reg 1 / r_ws $end
$var reg 1 0 r_ws_last $end
$var reg 1 ! valid $end
$var reg 5 1 word_counter [4:0] $end
$upscope $end
$upscope $end
$enddefinitions $end
$comment Show the parameter values. $end
$dumpall
b11000 *
b101 )
$end
#0
$dumpvars
b0 1
00
0/
0.
b0 -
b0 ,
b0 +
b0 (
b0 '
0&
0%
1$
0#
b0 "
0!
$end
#10
0$
#20
1$
#30
0$
#40
0%
b1 '
1$
1#
#50
0$
#60
1%
b10 '
1$
#70
0$
#80
1.
0%
b11 '
1$
#90
0$
#100
1%
0.
b100 '
1$
#110
0$
#120
1.
0%
b101 '
1$
#130
0$
#140
1%
0.
b110 '
1$
#150
0$
#160
1.
b111 '
1$
#170
0$
#180
b1000 '
1$
#190
0$
#200
b1001 '
1$
#210
0$
#220
0%
b1010 '
1$
#230
0$
#240
0.
b1011 '
1$
#250
0$
#260
1%
b1100 '
1$
#270
0$
#280
1.
b1101 '
1$
#290
0$
#300
0%
b1110 '
1$
#310
0$
#320
0.
1%
b1111 '
1$
#330
0$
#340
1.
b10000 '
1$
#350
0$
#360
b10001 '
1$
#370
0$
#380
b10010 '
1$
#390
0$
#400
0%
b10011 '
1$
#410
0$
#420
1%
0.
b10100 '
1$
#430
0$
#440
1.
b10101 '
1$
#450
0$
#460
b10110 '
1$
#470
0$
#480
b10111 '
1$
#490
0$
#500
0%
1&
b1 (
b0 '
1$
#510
0$
#520
0.
1/
b1 '
1$
#530
0$
#540
10
b1 1
b10 '
1$
#550
0$
#560
b10 1
1%
b11 '
1$
#570
0$
#580
0%
b11 1
1.
b100 '
1$
#590
0$
#600
b100 1
b100000000000000000000 ,
0.
b101 '
1$
#610
0$
#620
1%
b101 1
b110 '
1$
#630
0$
#640
b110 1
1.
0%
b111 '
1$
#650
0$
#660
b111 1
b100100000000000000000 ,
0.
b1000 '
1$
#670
0$
#680
b1000 1
b1001 '
1$
#690
0$
#700
1%
b1001 1
b1010 '
1$
#710
0$
#720
b1010 1
1.
b1011 '
1$
#730
0$
#740
0%
b1011 1
b100100010000000000000 ,
b1100 '
1$
#750
0$
#760
b1100 1
b100100011000000000000 ,
0.
1%
b1101 '
1$
#770
0$
#780
0%
b1101 1
1.
b1110 '
1$
#790
0$
#800
b1110 1
b100100011010000000000 ,
0.
b1111 '
1$
#810
0$
#820
b1111 1
b10000 '
1$
#830
0$
#840
b10000 1
1%
b10001 '
1$
#850
0$
#860
0%
b10001 1
1.
b10010 '
1$
#870
0$
#880
b10010 1
b100100011010001000000 ,
0.
1%
b10011 '
1$
#890
0$
#900
0%
b10011 1
1.
b10100 '
1$
#910
0$
#920
b10100 1
b100100011010001010000 ,
0.
1%
b10101 '
1$
#930
0$
#940
b10101 1
1.
b10110 '
1$
#950
0$
#960
b10110 1
b100100011010001010100 ,
0%
b10111 '
1$
#970
0$
#980
1%
0&
b10111 1
b100100011010001010110 ,
0.
b10 (
b0 '
1$
#990
0$
#1000
b100100011010001010110 "
b100100011010001010110 -
b0 1
1!
1.
0/
0%
b1 '
1$
#1010
0$
#1020
1%
b100000000000000000000000 +
00
b1 1
0!
0.
b10 '
1$
#1030
0$
#1040
b10 1
1.
b11 '
1$
#1050
0$
#1060
b11 1
b101000000000000000000000 +
b100 '
1$
#1070
0$
#1080
b100 1
b101100000000000000000000 +
0%
b101 '
1$
#1090
0$
#1100
1%
b101 1
b101110000000000000000000 +
0.
b110 '
1$
#1110
0$
#1120
b110 1
1.
0%
b111 '
1$
#1130
0$
#1140
1%
b111 1
b101110100000000000000000 +
0.
b1000 '
1$
#1150
0$
#1160
b1000 1
1.
b1001 '
1$
#1170
0$
#1180
0%
b1001 1
b101110101000000000000000 +
b1010 '
1$
#1190
0$
#1200
b1010 1
b101110101100000000000000 +
0.
1%
b1011 '
1$
#1210
0$
#1220
b1011 1
1.
b1100 '
1$
#1230
0$
#1240
b1100 1
b101110101101000000000000 +
0%
b1101 '
1$
#1250
0$
#1260
1%
b1101 1
b101110101101100000000000 +
0.
b1110 '
1$
#1270
0$
#1280
b1110 1
1.
b1111 '
1$
#1290
0$
#1300
b1111 1
b101110101101101000000000 +
b10000 '
1$
#1310
0$
#1320
b10000 1
b101110101101101100000000 +
0%
b10001 '
1$
#1330
0$
#1340
1%
b10001 1
b101110101101101110000000 +
0.
b10010 '
1$
#1350
0$
#1360
b10010 1
1.
0%
b10011 '
1$
#1370
0$
#1380
1%
b10011 1
b101110101101101110100000 +
0.
b10100 '
1$
#1390
0$
#1400
b10100 1
1.
b10101 '
1$
#1410
0$
#1420
0%
b10101 1
b101110101101101110101000 +
b10110 '
1$
#1430
0$
#1440
b10110 1
b101110101101101110101100 +
0.
1%
b10111 '
1$
#1450
0$
#1460
1&
b10111 1
1.
b11 (
b0 '
1$
#1470
0$
#1480
b101110101101101110101101 "
b101110101101101110101101 -
b0 1
1!
1/
b1 '
1$
#1490
0$
#1500
b100100100011010001010110 ,
10
b1 1
0!
b10 '
1$
#1510
0$
#1520
b10 1
b110100100011010001010110 ,
b11 '
1$
#1530
0$
#1540
0%
b11 1
b111100100011010001010110 ,
b100 '
1$
#1550
0$
#1560
b100 1
0.
b101 '
1$
#1570
0$
#1580
b101 1
b110 '
1$
#1590
0$
#1600
b110 1
b111 '
1$
#1610
0$
#1620
b111 1
b111100000011010001010110 ,
b1000 '
1$
#1630
0$
#1640
b1000 1
b1001 '
1$
#1650
0$
#1660
b1001 1
b1010 '
1$
#1670
0$
#1680
b1010 1
b1011 '
1$
#1690
0$
#1700
b1011 1
b111100000001010001010110 ,
b1100 '
1$
#1710
0$
#1720
b1100 1
b111100000000010001010110 ,
b1101 '
1$
#1730
0$
#1740
b1101 1
b1110 '
1$
#1750
0$
#1760
b1110 1
b111100000000000001010110 ,
b1111 '
1$
#1770
0$
#1780
b1111 1
b10000 '
1$
#1790
0$
#1800
b10000 1
b10001 '
1$
#1810
0$
#1820
b10001 1
b10010 '
1$
#1830
0$
#1840
b10010 1
b111100000000000000010110 ,
b10011 '
1$
#1850
0$
#1860
1%
b10011 1
b10100 '
1$
#1870
0$
#1880
b10100 1
b111100000000000000000110 ,
1.
b10101 '
1$
#1890
0$
#1900
0%
b10101 1
b111100000000000000001110 ,
b10110 '
1$
#1910
0$
#1920
b10110 1
0.
1%
b10111 '
1$
#1930
0$
#1940
b10111 1
b111100000000000000001100 ,
1.
b100 (
b11000 '
1$
#1950
0$
#1960
b111100000000000000001101 "
b111100000000000000001101 -
b0 1
1!
1$
#1970
0$
#1980
1$
#1990
0$
#2000
1$
#2010
0$
#2020
1$
#2030
0$
#2040
1$
