i2s.v
// LACKS AN ACK THAT MESSAGE WAS RECEIVED
// I'M AWARE THAT OUTPUT DATA IS HANDLED POORLY RIGHT NOW
// IF THE DESTINATION MISSED THE CLOCK CYCLE, DATA IS GONE
// KEEP IN MIND THAT THIS IS 1 CYCLE BEHIND
module transceiver #(
    parameter WIDTH = 24,
    parameter COUNTER_BITS = 5
)(
    input  wire        rst_n,
    input  wire        sck,
    input  wire        ws,
    input  wire        sd,
    output reg         valid,
    output reg  [WIDTH-1:0] data
); 

reg r_ws, r_sd; 
reg r_ws_last;

reg [COUNTER_BITS-1:0] word_counter;

reg [WIDTH-1:0] channel_1;
reg [WIDTH-1:0] channel_2;

always@(posedge sck) begin

    // reset logic
    if (!rst_n) begin
        // data is not valid, clear the garbage
        valid <= 1'b0;
        data <= 24'b0;

        r_sd <= 1'b0;

        r_ws <= ws;
        r_ws_last <= ws;

        // reset counter of bits within word
        word_counter <= 5'b0;

        // clear channels for safety (not strictly necessary)
        channel_1 <= 24'b0;
        channel_2 <= 24'b0;
    end

    else begin
        // latch my inputs
        r_ws <= ws;
        r_sd <= sd;

        // new word
        if (r_ws_last != r_ws) begin
            // *****CURRENT BUG*****
            // IS TAKING LAST WORD'S LSB BECAUSE CYCLE IS 1 BEHIND
            // IMPLEMENT PIPELINE OR HANDLE OTHERWISE

            // de-assert valid to indicate stale data
            valid <= 1'b0;

            // hardcode for safety
            word_counter <= 5'b1;

            // write MSB to correct channel, hardcode to MSB index for safety
            if (r_ws) channel_2[WIDTH-1] <= r_sd; 
            else      channel_1[WIDTH-1] <= r_sd;

            // update last WS variable to proceed in writing full word
            r_ws_last <= r_ws;
        
        // no new word
        end else begin

            if (word_counter == (WIDTH - 1)) begin
                // LAST CHARACTER WRITE

                // READS FROM LAST CYCLE BCZ LATCHING
                // when word_counter is 23, it will be writing to slot 0
                // hence, completed word
                valid <= 1;

                // reset word counter for next word
                word_counter <= 5'b0;

                // write data to appropriate channel
                if (r_ws) data <= channel_2;
                else      data <= channel_1;

            end else begin
                // STANDARD WRITE
                // will take effect next cycle
                word_counter <= word_counter + 1; // increment counter

                // write to correct bit
                if (r_ws) channel_2[23 - word_counter] <= r_sd;
                else      channel_1[23 - word_counter] <= r_sd;
            end
            
        end
    end
end

endmodule

i2s_tb.v
`timescale 1ns / 1ns
`include "i2s.v"

module i2s_tb;

  // -------------------------------------------------------------------------
  // UUT ports
  // -------------------------------------------------------------------------
  reg         i_rst_n;

  reg         i_sck = 0;
  reg         i_ws;
  reg         i_sd;

  wire        o_valid;
  wire [23:0] o_data;

  // -------------------------------------------------------------------------
  // Test vectors
  // -------------------------------------------------------------------------
  reg [23:0] src_data [0:3];   // a few words for the demo
  integer    data_counter;    // counts bits transmitted for the current word
  integer    word_counter;    // counts words transmitted

  // instantiate test module
  transceiver uut (
      .rst_n (i_rst_n),
      .sck   (i_sck),
      .ws    (i_ws),
      .sd    (i_sd),
      .valid (o_valid),
      .data  (o_data)
  );

  // toggle clock every 10ns (20ns cycle time)
  always begin
    i_sck = ~i_sck;
    #10;
  end

  



  // -------------------------------------------------------------------------
  // Test stimulus
  // -------------------------------------------------------------------------
  initial begin
    // -------------------------------------------------
    // Dump waveform for later inspection
    // -------------------------------------------------
    $dumpfile("i2s_tb.vcd");
    $dumpvars(0, i2s_tb);

    // -------------------------------------------------
    // Initialise registers
    // -------------------------------------------------
    i_rst_n = 0;          // keep DUT in reset initially
    i_ws    = 0;
    i_sd    = 0;
    data_counter = 0;
    word_counter = 0;

    // -------------------------------------------------
    // Test words (6 HEX CHARACTERS * 4bit per = 24 bit per word)
    // -------------------------------------------------

    // src_data[0] = 24'hABCDEF;
    // src_data[1] = 24'h123456;
    // src_data[2] = 24'hBADBAD;
    // src_data[3] = 24'hF0000D;

    // alternating high-low switching - easy to spot in waveform
    // to check that data is being transmitted properly
    src_data[0] = 24'b010101010101010101010101; // 1-1-1-1
    src_data[1] = 24'b001100110011001100110011; // 2-2-2-2
    src_data[2] = 24'b000111000111000111000111; // 3-3-3-3
    src_data[3] = 24'b000011110000111100001111; // 4-4-4-4

    // -------------------------------------------------
    // Release reset after a couple of clock edges
    // -------------------------------------------------
    #40 i_rst_n = 1;  // de‑assert reset

    // -------------------------------------------------
    // Transmit all words, LSB‑first, one bit per clock
    // -------------------------------------------------
    for (word_counter = 0; word_counter < 4; word_counter = word_counter + 1) begin
      // WS is high for the left channel, low for the right channel.
      // For simplicity we toggle it every 32 bits.
      i_ws <= word_counter[0];   // 0,1,0,1 … (alternates each word)

      // Send 24 bits of the current word, MSB first
      for (data_counter = 0; data_counter < 24; data_counter = data_counter + 1) begin
        // Subtract from 23 to grab the top bits first
        i_sd <= src_data[word_counter][23 - data_counter]; 
        @(posedge i_sck);
      end
    end

    // -------------------------------------------------
    // 6Wait for the DUT to raise `valid` and capture the last word
    // -------------------------------------------------
    // @(posedge o_valid);
    // $display("----- Received word -----");
    // $display("  Expected : %h", src_data[word_counter-1]);
    // $display("  DUT out  : %h", o_data);
    // $display("--------------------------");

    // -------------------------------------------------
    // Finish simulation
    // -------------------------------------------------
    #100 $finish;
  end

endmodule

i2s_tb.vcd
$date
	Wed Jun  3 22:59:55 2026
$end
$version
	Icarus Verilog
$end
$timescale
	1ns
$end
$scope module i2s_tb $end
$var wire 1 ! o_valid $end
$var wire 24 " o_data [23:0] $end
$var reg 1 # i_rst_n $end
$var reg 1 $ i_sck $end
$var reg 1 % i_sd $end
$var reg 1 & i_ws $end
$var integer 32 ' data_counter [31:0] $end
$var integer 32 ( word_counter [31:0] $end
$scope module uut $end
$var wire 1 # rst_n $end
$var wire 1 $ sck $end
$var wire 1 % sd $end
$var wire 1 & ws $end
$var parameter 32 ) COUNTER_BITS $end
$var parameter 32 * WIDTH $end
$var reg 24 + channel_1 [23:0] $end
$var reg 24 , channel_2 [23:0] $end
$var reg 24 - data [23:0] $end
$var reg 1 . r_sd $end
$var reg 1 / r_ws $end
$var reg 1 0 r_ws_last $end
$var reg 1 ! valid $end
$var reg 5 1 word_counter [4:0] $end
$upscope $end
$upscope $end
$enddefinitions $end
$comment Show the parameter values. $end
$dumpall
b11000 *
b101 )
$end
#0
$dumpvars
b0 1
00
0/
0.
b0 -
b0 ,
b0 +
b0 (
b0 '
0&
0%
1$
0#
b0 "
0!
$end
#10
0$
#20
1$
#30
0$
#40
b1 1
1%
b1 '
1$
1#
#50
0$
#60
0%
b10 1
1.
b10 '
1$
#70
0$
#80
b1000000000000000000000 +
b11 1
0.
1%
b11 '
1$
#90
0$
#100
0%
b100 1
1.
b100 '
1$
#110
0$
#120
b1010000000000000000000 +
b101 1
0.
1%
b101 '
1$
#130
0$
#140
0%
b110 1
1.
b110 '
1$
#150
0$
#160
b1010100000000000000000 +
b111 1
0.
1%
b111 '
1$
#170
0$
#180
0%
b1000 1
1.
b1000 '
1$
#190
0$
#200
b1010101000000000000000 +
b1001 1
0.
1%
b1001 '
1$
#210
0$
#220
0%
b1010 1
1.
b1010 '
1$
#230
0$
#240
b1010101010000000000000 +
b1011 1
0.
1%
b1011 '
1$
#250
0$
#260
0%
b1100 1
1.
b1100 '
1$
#270
0$
#280
b1010101010100000000000 +
b1101 1
0.
1%
b1101 '
1$
#290
0$
#300
0%
b1110 1
1.
b1110 '
1$
#310
0$
#320
b1010101010101000000000 +
b1111 1
0.
1%
b1111 '
1$
#330
0$
#340
0%
b10000 1
1.
b10000 '
1$
#350
0$
#360
b1010101010101010000000 +
b10001 1
0.
1%
b10001 '
1$
#370
0$
#380
0%
b10010 1
1.
b10010 '
1$
#390
0$
#400
b1010101010101010100000 +
b10011 1
0.
1%
b10011 '
1$
#410
0$
#420
0%
b10100 1
1.
b10100 '
1$
#430
0$
#440
b1010101010101010101000 +
b10101 1
0.
1%
b10101 '
1$
#450
0$
#460
0%
b10110 1
1.
b10110 '
1$
#470
0$
#480
b1010101010101010101010 +
b10111 1
0.
1%
b10111 '
1$
#490
0$
#500
0%
1&
b1010101010101010101010 "
b1010101010101010101010 -
b0 1
1!
1.
b1 (
b0 '
1$
#510
0$
#520
b101010101010101010101010 +
b1 1
0.
1/
b1 '
1$
#530
0$
#540
1%
10
0!
b10 '
1$
#550
0$
#560
b10 1
1.
b11 '
1$
#570
0$
#580
0%
b1000000000000000000000 ,
b11 1
b100 '
1$
#590
0$
#600
b1100000000000000000000 ,
b100 1
0.
b101 '
1$
#610
0$
#620
1%
b101 1
b110 '
1$
#630
0$
#640
b110 1
1.
b111 '
1$
#650
0$
#660
0%
b1100100000000000000000 ,
b111 1
b1000 '
1$
#670
0$
#680
b1100110000000000000000 ,
b1000 1
0.
b1001 '
1$
#690
0$
#700
1%
b1001 1
b1010 '
1$
#710
0$
#720
b1010 1
1.
b1011 '
1$
#730
0$
#740
0%
b1100110010000000000000 ,
b1011 1
b1100 '
1$
#750
0$
#760
b1100110011000000000000 ,
b1100 1
0.
b1101 '
1$
#770
0$
#780
1%
b1101 1
b1110 '
1$
#790
0$
#800
b1110 1
1.
b1111 '
1$
#810
0$
#820
0%
b1100110011001000000000 ,
b1111 1
b10000 '
1$
#830
0$
#840
b1100110011001100000000 ,
b10000 1
0.
b10001 '
1$
#850
0$
#860
1%
b10001 1
b10010 '
1$
#870
0$
#880
b10010 1
1.
b10011 '
1$
#890
0$
#900
0%
b1100110011001100100000 ,
b10011 1
b10100 '
1$
#910
0$
#920
b1100110011001100110000 ,
b10100 1
0.
b10101 '
1$
#930
0$
#940
1%
b10101 1
b10110 '
1$
#950
0$
#960
b10110 1
1.
b10111 '
1$
#970
0$
#980
0%
0&
b1100110011001100110010 ,
b10111 1
b10 (
b0 '
1$
#990
0$
#1000
b1100110011001100110010 "
b1100110011001100110010 -
b0 1
1!
0.
0/
b1 '
1$
#1010
0$
#1020
00
b1010101010101010101010 +
b1 1
0!
b10 '
1$
#1030
0$
#1040
b10 1
1%
b11 '
1$
#1050
0$
#1060
b10101010101010101010 +
b11 1
1.
b100 '
1$
#1070
0$
#1080
b110101010101010101010 +
b100 1
b101 '
1$
#1090
0$
#1100
0%
b101 1
b110 '
1$
#1110
0$
#1120
b111101010101010101010 +
b110 1
0.
b111 '
1$
#1130
0$
#1140
b111001010101010101010 +
b111 1
b1000 '
1$
#1150
0$
#1160
b1000 1
1%
b1001 '
1$
#1170
0$
#1180
b111000010101010101010 +
b1001 1
1.
b1010 '
1$
#1190
0$
#1200
b111000110101010101010 +
b1010 1
b1011 '
1$
#1210
0$
#1220
0%
b1011 1
b1100 '
1$
#1230
0$
#1240
b111000111101010101010 +
b1100 1
0.
b1101 '
1$
#1250
0$
#1260
b111000111001010101010 +
b1101 1
b1110 '
1$
#1270
0$
#1280
b1110 1
1%
b1111 '
1$
#1290
0$
#1300
b111000111000010101010 +
b1111 1
1.
b10000 '
1$
#1310
0$
#1320
b111000111000110101010 +
b10000 1
b10001 '
1$
#1330
0$
#1340
0%
b10001 1
b10010 '
1$
#1350
0$
#1360
b111000111000111101010 +
b10010 1
0.
b10011 '
1$
#1370
0$
#1380
b111000111000111001010 +
b10011 1
b10100 '
1$
#1390
0$
#1400
b10100 1
1%
b10101 '
1$
#1410
0$
#1420
b111000111000111000010 +
b10101 1
1.
b10110 '
1$
#1430
0$
#1440
b111000111000111000110 +
b10110 1
b10111 '
1$
#1450
0$
#1460
0%
1&
b10111 1
b11 (
b0 '
1$
#1470
0$
#1480
b111000111000111000110 "
b111000111000111000110 -
b0 1
1!
0.
1/
b1 '
1$
#1490
0$
#1500
10
b1 1
0!
b10 '
1$
#1510
0$
#1520
b10 1
b11 '
1$
#1530
0$
#1540
1%
b100110011001100110010 ,
b11 1
b100 '
1$
#1550
0$
#1560
b110011001100110010 ,
b100 1
1.
b101 '
1$
#1570
0$
#1580
b10110011001100110010 ,
b101 1
b110 '
1$
#1590
0$
#1600
b11110011001100110010 ,
b110 1
b111 '
1$
#1610
0$
#1620
0%
b111 1
b1000 '
1$
#1630
0$
#1640
b1000 1
0.
b1001 '
1$
#1650
0$
#1660
b1001 1
b1010 '
1$
#1670
0$
#1680
b1010 1
b1011 '
1$
#1690
0$
#1700
1%
b11110001001100110010 ,
b1011 1
b1100 '
1$
#1710
0$
#1720
b11110000001100110010 ,
b1100 1
1.
b1101 '
1$
#1730
0$
#1740
b11110000101100110010 ,
b1101 1
b1110 '
1$
#1750
0$
#1760
b11110000111100110010 ,
b1110 1
b1111 '
1$
#1770
0$
#1780
0%
b1111 1
b10000 '
1$
#1790
0$
#1800
b10000 1
0.
b10001 '
1$
#1810
0$
#1820
b10001 1
b10010 '
1$
#1830
0$
#1840
b10010 1
b10011 '
1$
#1850
0$
#1860
1%
b11110000111100010010 ,
b10011 1
b10100 '
1$
#1870
0$
#1880
b11110000111100000010 ,
b10100 1
1.
b10101 '
1$
#1890
0$
#1900
b11110000111100001010 ,
b10101 1
b10110 '
1$
#1910
0$
#1920
b11110000111100001110 ,
b10110 1
b10111 '
1$
#1930
0$
#1940
b10111 1
b100 (
b11000 '
1$
#1950
0$
#1960
b11110000111100001110 "
b11110000111100001110 -
b0 1
1!
1$
#1970
0$
#1980
b100011110000111100001110 ,
b1 1
1$
#1990
0$
#2000
b110011110000111100001110 ,
b10 1
1$
#2010
0$
#2020
b111011110000111100001110 ,
b11 1
1$
#2030
0$
#2040
b111111110000111100001110 ,
b100 1
1$
